solvis_results_api/__init__.py
solvis_results_api/get_devices.py
solvis_results_api/get_evaluations.py
solvis_results_api/get_questionnaire.py
solvis_results_api/get_surveyed_units.py
solvis_results_api/get_suspicious_occurrences.py
solvis_results_api/process_evaluations.py
solvis_results_api-0.1.5.dist-info/METADATA
solvis_results_api-0.1.5.dist-info/WHEEL
solvis_results_api-0.1.5.dist-info/licenses/LICENSE
solvis_results_api-0.1.5.dist-info/RECORD
