Metadata-Version: 2.4
Name: solvis-results-api
Version: 0.1.5
Summary: This is a package for requesting and processing data from Solvis's results API.
Author-email: Paulo Victor <paulo.barbosa@solvis.com.br>
License-File: LICENSE
Requires-Python: >=3.12
Requires-Dist: pandas>=2.2.3
Requires-Dist: requests>=2.32.3
